README.md
setup.py
gchatUts/__init__.py
gchatUts/default.json
gchatUts/uikit.py
gchatUts.egg-info/PKG-INFO
gchatUts.egg-info/SOURCES.txt
gchatUts.egg-info/dependency_links.txt
gchatUts.egg-info/requires.txt
gchatUts.egg-info/top_level.txt
gchatUts/sections/__init__.py
gchatUts/sections/error.py
gchatUts/sections/etapa.json
gchatUts/sections/etapa.py
gchatUts/sections/resumo.json
gchatUts/sections/resumo.py
gchatUts/sections/success.py
gchatUts/sections/text.py
gchatUts/sections/warn.py