Metadata-Version: 2.1
Name: gchatUts
Version: 1.0.2
Summary: Lib para comunicação via Google Chat Web Hook
Home-page: 
Author: Zdek
Author-email: 
License: MIT
Keywords: gChat
Classifier: Development Status :: 5 - Production/Stable
Classifier: Intended Audience :: Education
Classifier: Operating System :: Microsoft :: Windows :: Windows 10
Classifier: License :: OSI Approved :: MIT License
Classifier: Programming Language :: Python :: 3
Requires-Dist: requests>=2.7.0
